{
	"info": {
		"_postman_id": "37ff9edb-8dd6-4c4e-843e-3195db7097d1",
		"name": "Pofile-API",
		"schema": "https://schema.getpostman.com/json/collection/v2.1.0/collection.json",
		"_exporter_id": "8152158"
	},
	"item": [
		{
			"name": "TypeDocument",
			"item": [
				{
					"name": "saveTypeDocument",
					"request": {
						"method": "POST",
						"header": [],
						"body": {
							"mode": "raw",
							"raw": "{\n    \"name\": \"otro\"\n}",
							"options": {
								"raw": {
									"language": "json"
								}
							}
						},
						"url": {
							"raw": "http://localhost:8050/api/v1/typedocuments/save",
							"protocol": "http",
							"host": [
								"localhost"
							],
							"port": "8050",
							"path": [
								"api",
								"v1",
								"typedocuments",
								"save"
							]
						}
					},
					"response": []
				},
				{
					"name": "getAll",
					"request": {
						"method": "GET",
						"header": [],
						"url": {
							"raw": "http://localhost:8050/api/v1/typedocuments/all",
							"protocol": "http",
							"host": [
								"localhost"
							],
							"port": "8050",
							"path": [
								"api",
								"v1",
								"typedocuments",
								"all"
							]
						}
					},
					"response": []
				},
				{
					"name": "getTypeDocumentById",
					"request": {
						"method": "GET",
						"header": [],
						"url": {
							"raw": "http://localhost:8050/api/v1/typedocuments/2",
							"protocol": "http",
							"host": [
								"localhost"
							],
							"port": "8050",
							"path": [
								"api",
								"v1",
								"typedocuments",
								"2"
							]
						}
					},
					"response": []
				},
				{
					"name": "deleteTypeDocumentById",
					"request": {
						"method": "DELETE",
						"header": [],
						"url": {
							"raw": "http://localhost:8050/api/v1/typedocuments/delete/4",
							"protocol": "http",
							"host": [
								"localhost"
							],
							"port": "8050",
							"path": [
								"api",
								"v1",
								"typedocuments",
								"delete",
								"4"
							]
						}
					},
					"response": []
				}
			]
		},
		{
			"name": "User",
			"item": [
				{
					"name": "saveUser",
					"request": {
						"method": "POST",
						"header": [],
						"body": {
							"mode": "raw",
							"raw": "{\n    \"identicationNumber\": \"8888889\",\n    \"name\": \"PersonaTest\",\n    \"typeDocumentId\": 1,\n    \"mail\": \"nueve@mail.com\",\n    \"phone\": \"+56900912283\",\n    \"addressId\": 10,\n    \"skill\": \"Tengo habilidades en java, react, sql, mongodb, excel, tbleau y word\",\n    \"changeOfResidence\": true,\n    \"birthday\": \"28-03-1985\",\n    \"age\": \"37\",\n    \"profileId\": 13\n}",
							"options": {
								"raw": {
									"language": "json"
								}
							}
						},
						"url": {
							"raw": "http://localhost:8050/api/v1/users/save",
							"protocol": "http",
							"host": [
								"localhost"
							],
							"port": "8050",
							"path": [
								"api",
								"v1",
								"users",
								"save"
							]
						}
					},
					"response": []
				},
				{
					"name": "getAllUsers",
					"request": {
						"method": "GET",
						"header": [],
						"url": {
							"raw": "http://localhost:8050/api/v1/users/all",
							"protocol": "http",
							"host": [
								"localhost"
							],
							"port": "8050",
							"path": [
								"api",
								"v1",
								"users",
								"all"
							]
						}
					},
					"response": []
				},
				{
					"name": "getAllUsersBySkill",
					"request": {
						"method": "GET",
						"header": [],
						"url": {
							"raw": "http://localhost:8050/api/v1/users/all/skill/ux",
							"protocol": "http",
							"host": [
								"localhost"
							],
							"port": "8050",
							"path": [
								"api",
								"v1",
								"users",
								"all",
								"skill",
								"ux"
							]
						}
					},
					"response": []
				},
				{
					"name": "getAllUsersYears",
					"request": {
						"method": "GET",
						"header": [],
						"url": {
							"raw": "http://localhost:8050/api/v1/users/all/years/8",
							"protocol": "http",
							"host": [
								"localhost"
							],
							"port": "8050",
							"path": [
								"api",
								"v1",
								"users",
								"all",
								"years",
								"8"
							]
						}
					},
					"response": []
				},
				{
					"name": "getAllUsersByProfileMasterAndDoctorate",
					"request": {
						"method": "GET",
						"header": [],
						"url": {
							"raw": "http://localhost:8050/api/v1/users/all/doctorate_o_master",
							"protocol": "http",
							"host": [
								"localhost"
							],
							"port": "8050",
							"path": [
								"api",
								"v1",
								"users",
								"all",
								"doctorate_o_master"
							]
						}
					},
					"response": []
				},
				{
					"name": "getAllUsersByProfileCityOrCountry",
					"request": {
						"method": "GET",
						"header": [],
						"url": {
							"raw": "http://localhost:8050/api/v1/users/all/city_or_country/santiago/chile",
							"protocol": "http",
							"host": [
								"localhost"
							],
							"port": "8050",
							"path": [
								"api",
								"v1",
								"users",
								"all",
								"city_or_country",
								"santiago",
								"chile"
							]
						}
					},
					"response": []
				},
				{
					"name": "getAllUsersByChangeOfResidence",
					"request": {
						"method": "GET",
						"header": [],
						"url": {
							"raw": "http://localhost:8050/api/v1/users/all/chageOfResidence",
							"protocol": "http",
							"host": [
								"localhost"
							],
							"port": "8050",
							"path": [
								"api",
								"v1",
								"users",
								"all",
								"chageOfResidence"
							]
						}
					},
					"response": []
				},
				{
					"name": "getAllUsersPreGrade",
					"request": {
						"method": "GET",
						"header": [],
						"url": {
							"raw": "http://localhost:8050/api/v1/users/all/pregrade",
							"protocol": "http",
							"host": [
								"localhost"
							],
							"port": "8050",
							"path": [
								"api",
								"v1",
								"users",
								"all",
								"pregrade"
							]
						}
					},
					"response": []
				},
				{
					"name": "getUserById",
					"request": {
						"method": "GET",
						"header": [],
						"url": {
							"raw": "http://localhost:8050/api/v1/users/16",
							"protocol": "http",
							"host": [
								"localhost"
							],
							"port": "8050",
							"path": [
								"api",
								"v1",
								"users",
								"16"
							]
						}
					},
					"response": []
				},
				{
					"name": "deleteUserById",
					"request": {
						"method": "DELETE",
						"header": [],
						"url": {
							"raw": "http://localhost:8050/api/v1/users/delete/19",
							"protocol": "http",
							"host": [
								"localhost"
							],
							"port": "8050",
							"path": [
								"api",
								"v1",
								"users",
								"delete",
								"19"
							]
						}
					},
					"response": []
				}
			]
		},
		{
			"name": "Profile",
			"item": [
				{
					"name": "saveProfile",
					"request": {
						"method": "POST",
						"header": [],
						"body": {
							"mode": "raw",
							"raw": "{\n    \"aboutMe\" : \"Otro profile para probar las VALIDACIONES\"\n}",
							"options": {
								"raw": {
									"language": "json"
								}
							}
						},
						"url": {
							"raw": "http://localhost:8050/api/v1/profiles/save",
							"protocol": "http",
							"host": [
								"localhost"
							],
							"port": "8050",
							"path": [
								"api",
								"v1",
								"profiles",
								"save"
							]
						}
					},
					"response": []
				},
				{
					"name": "getAll",
					"request": {
						"method": "GET",
						"header": [],
						"url": {
							"raw": "http://localhost:8050/api/v1/profiles/all",
							"protocol": "http",
							"host": [
								"localhost"
							],
							"port": "8050",
							"path": [
								"api",
								"v1",
								"profiles",
								"all"
							]
						}
					},
					"response": []
				},
				{
					"name": "getProfileById",
					"request": {
						"method": "GET",
						"header": [],
						"url": {
							"raw": "http://localhost:8050/api/v1/profiles/1",
							"protocol": "http",
							"host": [
								"localhost"
							],
							"port": "8050",
							"path": [
								"api",
								"v1",
								"profiles",
								"1"
							]
						}
					},
					"response": []
				},
				{
					"name": "deleteProfileById",
					"request": {
						"method": "DELETE",
						"header": [],
						"url": {
							"raw": "http://localhost:8050/api/v1/profiles/delete/7",
							"protocol": "http",
							"host": [
								"localhost"
							],
							"port": "8050",
							"path": [
								"api",
								"v1",
								"profiles",
								"delete",
								"7"
							]
						}
					},
					"response": []
				}
			]
		},
		{
			"name": "Experience",
			"item": [
				{
					"name": "saveExperience",
					"request": {
						"method": "POST",
						"header": [],
						"body": {
							"mode": "raw",
							"raw": "{\n    \"positionName\" : \"Borrar\",\n    \"companyName\" : \"Prueba Borrar\",\n    \"startDate\" : \"22-07-2020\",\n    \"endDate\" : \"22-07-2022\",\n    \"country\" : \"Chile\",\n    \"description\" : \"is simply dummy text of the printing and typesetting industry. Lorem Ipsum has been the industry's standard dummy text ever since the 1500s\",\n    \"profileId\": 13\n}",
							"options": {
								"raw": {
									"language": "json"
								}
							}
						},
						"url": {
							"raw": "http://localhost:8050/api/v1/experiences/save",
							"protocol": "http",
							"host": [
								"localhost"
							],
							"port": "8050",
							"path": [
								"api",
								"v1",
								"experiences",
								"save"
							]
						}
					},
					"response": []
				},
				{
					"name": "getAll",
					"request": {
						"method": "GET",
						"header": [],
						"url": {
							"raw": "http://localhost:8050/api/v1/experiences/all",
							"protocol": "http",
							"host": [
								"localhost"
							],
							"port": "8050",
							"path": [
								"api",
								"v1",
								"experiences",
								"all"
							]
						}
					},
					"response": []
				},
				{
					"name": "getExperienceById",
					"request": {
						"method": "GET",
						"header": [],
						"url": {
							"raw": "http://localhost:8050/api/v1/experiences/1",
							"protocol": "http",
							"host": [
								"localhost"
							],
							"port": "8050",
							"path": [
								"api",
								"v1",
								"experiences",
								"1"
							]
						}
					},
					"response": []
				},
				{
					"name": "deleteExperienceById",
					"request": {
						"method": "DELETE",
						"header": [],
						"url": {
							"raw": "http://localhost:8050/api/v1/experiences/delete/4",
							"protocol": "http",
							"host": [
								"localhost"
							],
							"port": "8050",
							"path": [
								"api",
								"v1",
								"experiences",
								"delete",
								"4"
							]
						}
					},
					"response": []
				}
			]
		},
		{
			"name": "EducationLevel",
			"item": [
				{
					"name": "saveEducationLevel",
					"request": {
						"method": "POST",
						"header": [],
						"body": {
							"mode": "raw",
							"raw": "{\n    \"degree\" : \"BORRAR\"\n\n}",
							"options": {
								"raw": {
									"language": "json"
								}
							}
						},
						"url": {
							"raw": "http://localhost:8050/api/v1/educationLevels/save",
							"protocol": "http",
							"host": [
								"localhost"
							],
							"port": "8050",
							"path": [
								"api",
								"v1",
								"educationLevels",
								"save"
							]
						}
					},
					"response": []
				},
				{
					"name": "updateEducationLevel",
					"request": {
						"method": "POST",
						"header": [],
						"body": {
							"mode": "raw",
							"raw": "{\n        \"estado\": \"1\",\n        \"educationLevelId\": 9,\n        \"degree\": \"BORRAR\"\n}",
							"options": {
								"raw": {
									"language": "json"
								}
							}
						},
						"url": {
							"raw": "http://localhost:8050/api/v1/educationLevels/update",
							"protocol": "http",
							"host": [
								"localhost"
							],
							"port": "8050",
							"path": [
								"api",
								"v1",
								"educationLevels",
								"update"
							]
						}
					},
					"response": []
				},
				{
					"name": "getAllEducationLevel",
					"request": {
						"method": "GET",
						"header": [],
						"url": {
							"raw": "http://localhost:8050/api/v1/educationLevels/all",
							"protocol": "http",
							"host": [
								"localhost"
							],
							"port": "8050",
							"path": [
								"api",
								"v1",
								"educationLevels",
								"all"
							]
						}
					},
					"response": []
				},
				{
					"name": "getEducationLevelById",
					"request": {
						"method": "GET",
						"header": [],
						"url": {
							"raw": "http://localhost:8050/api/v1/educationLevels/1",
							"protocol": "http",
							"host": [
								"localhost"
							],
							"port": "8050",
							"path": [
								"api",
								"v1",
								"educationLevels",
								"1"
							]
						}
					},
					"response": []
				},
				{
					"name": "deleteEducationLevelById",
					"request": {
						"method": "DELETE",
						"header": [],
						"body": {
							"mode": "raw",
							"raw": "{\n    \"estado\" : \"0\"\n\n}",
							"options": {
								"raw": {
									"language": "json"
								}
							}
						},
						"url": {
							"raw": "http://localhost:8050/api/v1/educationLevels/delete/9",
							"protocol": "http",
							"host": [
								"localhost"
							],
							"port": "8050",
							"path": [
								"api",
								"v1",
								"educationLevels",
								"delete",
								"9"
							]
						}
					},
					"response": []
				}
			]
		},
		{
			"name": "Education",
			"item": [
				{
					"name": "saveEducation",
					"request": {
						"method": "POST",
						"header": [],
						"body": {
							"mode": "raw",
							"raw": "{\n    \"institutionName\" : \"Borrar1\",\n    \"description\" : \"Lorem Ipsum is simply dummy text of the printing and typesetting industry. Lorem Ipsum has been the industry's standard dummy text ever since the 1500s\",\n    \"startDate\" : \"22-07-2018\",\n    \"endDate\" : \"22-07-2020\",\n    \"nameOfTitle\" : \"Para Borrar\",\n    \"profileId\": 1,\n    \"educationLevelId\" : 9\n\n}",
							"options": {
								"raw": {
									"language": "json"
								}
							}
						},
						"url": {
							"raw": "http://localhost:8050/api/v1/educations/save",
							"protocol": "http",
							"host": [
								"localhost"
							],
							"port": "8050",
							"path": [
								"api",
								"v1",
								"educations",
								"save"
							]
						}
					},
					"response": []
				},
				{
					"name": "updateEducation",
					"request": {
						"method": "POST",
						"header": [],
						"body": {
							"mode": "raw",
							"raw": "{\n    \"educationId\": 7,\n    \"institutionName\" : \"Borrar1 MOdificado\",\n    \"description\" : \"Lorem Ipsum is simply dummy text of the printing and typesetting industry. Lorem Ipsum has been the industry's standard dummy text ever since the 1500s\",\n    \"startDate\" : \"22-07-2018\",\n    \"endDate\" : \"22-07-2020\",\n    \"nameOfTitle\" : \"Para Borrar Modificado\",\n    \"profileId\": 1,\n    \"educationLevelId\" : 9\n}",
							"options": {
								"raw": {
									"language": "json"
								}
							}
						},
						"url": {
							"raw": "http://localhost:8050/api/v1/educations/update",
							"protocol": "http",
							"host": [
								"localhost"
							],
							"port": "8050",
							"path": [
								"api",
								"v1",
								"educations",
								"update"
							]
						}
					},
					"response": []
				},
				{
					"name": "getAllEducation",
					"request": {
						"method": "GET",
						"header": [],
						"url": {
							"raw": "http://localhost:8050/api/v1/educations/all",
							"protocol": "http",
							"host": [
								"localhost"
							],
							"port": "8050",
							"path": [
								"api",
								"v1",
								"educations",
								"all"
							]
						}
					},
					"response": []
				},
				{
					"name": "getEducationById",
					"request": {
						"method": "GET",
						"header": [],
						"url": {
							"raw": "http://localhost:8050/api/v1/educations/7",
							"protocol": "http",
							"host": [
								"localhost"
							],
							"port": "8050",
							"path": [
								"api",
								"v1",
								"educations",
								"7"
							]
						}
					},
					"response": []
				},
				{
					"name": "deleteEducationById",
					"request": {
						"method": "DELETE",
						"header": [],
						"body": {
							"mode": "raw",
							"raw": "{\n    \"estado\" : \"0\"\n\n}",
							"options": {
								"raw": {
									"language": "json"
								}
							}
						},
						"url": {
							"raw": "http://localhost:8050/api/v1/educations/delete/7",
							"protocol": "http",
							"host": [
								"localhost"
							],
							"port": "8050",
							"path": [
								"api",
								"v1",
								"educations",
								"delete",
								"7"
							]
						}
					},
					"response": []
				}
			]
		},
		{
			"name": "Certificate",
			"item": [
				{
					"name": "saveCertificate",
					"request": {
						"method": "POST",
						"header": [],
						"body": {
							"mode": "raw",
							"raw": "{\n    \"name\" : \"Certificado3 Para Borrar\",\n    \"description\" : \"Lorem Ipsum is simply dummy text of the printing and typesetting industry. Lorem Ipsum has been the industry's standard dummy text ever since the 1500s\",\n    \"startDate\" : \"22-08-2019\",\n    \"endDate\" : \"15-08-2022\",\n    \"institution\" : \"Centro Educacional 3 Para Borrar\",\n    \"profileId\": 1,\n    \"educationLevelId\" : 10\n\n}",
							"options": {
								"raw": {
									"language": "json"
								}
							}
						},
						"url": {
							"raw": "http://localhost:8050/api/v1/certificates/save",
							"protocol": "http",
							"host": [
								"localhost"
							],
							"port": "8050",
							"path": [
								"api",
								"v1",
								"certificates",
								"save"
							]
						}
					},
					"response": []
				},
				{
					"name": "updateCertificate",
					"request": {
						"method": "POST",
						"header": [],
						"body": {
							"mode": "raw",
							"raw": "{\n    \"certificateId\": 1,\n    \"name\" : \"Certificado2\",\n    \"description\" : \"Lorem Ipsum is simply dummy text of the printing and typesetting industry. Lorem Ipsum has been the industry's standard dummy text ever since the 1500s\",\n    \"startDate\" : \"22-08-2019\",\n    \"endDate\" : \"15-08-2022\",\n    \"institution\" : \"Centro Educacional 2\",\n    \"profileId\": 1,\n    \"educationLevelId\" : 3\n\n}",
							"options": {
								"raw": {
									"language": "json"
								}
							}
						},
						"url": {
							"raw": "http://localhost:8050/api/v1/certificates/update",
							"protocol": "http",
							"host": [
								"localhost"
							],
							"port": "8050",
							"path": [
								"api",
								"v1",
								"certificates",
								"update"
							]
						}
					},
					"response": []
				},
				{
					"name": "getAllCertificate",
					"request": {
						"method": "GET",
						"header": [],
						"url": {
							"raw": "http://localhost:8050/api/v1/certificates/all",
							"protocol": "http",
							"host": [
								"localhost"
							],
							"port": "8050",
							"path": [
								"api",
								"v1",
								"certificates",
								"all"
							]
						}
					},
					"response": []
				},
				{
					"name": "getCertificateById",
					"request": {
						"method": "GET",
						"header": [],
						"url": {
							"raw": "http://localhost:8050/api/v1/certificates/1",
							"protocol": "http",
							"host": [
								"localhost"
							],
							"port": "8050",
							"path": [
								"api",
								"v1",
								"certificates",
								"1"
							]
						}
					},
					"response": []
				},
				{
					"name": "deleteCertificateById",
					"request": {
						"method": "DELETE",
						"header": [],
						"body": {
							"mode": "raw",
							"raw": "{\n    \"estado\" : \"0\"\n\n}",
							"options": {
								"raw": {
									"language": "json"
								}
							}
						},
						"url": {
							"raw": "http://localhost:8050/api/v1/certificates/delete/3",
							"protocol": "http",
							"host": [
								"localhost"
							],
							"port": "8050",
							"path": [
								"api",
								"v1",
								"certificates",
								"delete",
								"3"
							]
						}
					},
					"response": []
				}
			]
		},
		{
			"name": "Address",
			"item": [
				{
					"name": "getAll",
					"request": {
						"method": "GET",
						"header": [],
						"url": {
							"raw": "http://localhost:8050/api/v1/addresses/all",
							"protocol": "http",
							"host": [
								"localhost"
							],
							"port": "8050",
							"path": [
								"api",
								"v1",
								"addresses",
								"all"
							]
						}
					},
					"response": []
				},
				{
					"name": "saveAddress",
					"request": {
						"method": "POST",
						"header": [],
						"body": {
							"mode": "raw",
							"raw": "{\n    \"city\": \"Ciudad Prueba\",\n    \"country\": \"Pais Prueba\",\n    \"postalCode\": \"22222\",\n    \"street\": \"Calle de Prueba 22222 casa j, Lo Prueba\"\n}",
							"options": {
								"raw": {
									"language": "json"
								}
							}
						},
						"url": {
							"raw": "http://localhost:8050/api/v1/addresses/save",
							"protocol": "http",
							"host": [
								"localhost"
							],
							"port": "8050",
							"path": [
								"api",
								"v1",
								"addresses",
								"save"
							]
						}
					},
					"response": []
				},
				{
					"name": "getAddressById",
					"request": {
						"method": "GET",
						"header": [],
						"url": {
							"raw": "http://localhost:8050/api/v1/addresses/4",
							"protocol": "http",
							"host": [
								"localhost"
							],
							"port": "8050",
							"path": [
								"api",
								"v1",
								"addresses",
								"4"
							]
						}
					},
					"response": []
				},
				{
					"name": "deleteAddressById",
					"request": {
						"method": "DELETE",
						"header": [],
						"url": {
							"raw": "http://localhost:8050/api/v1/addresses/delete/4",
							"protocol": "http",
							"host": [
								"localhost"
							],
							"port": "8050",
							"path": [
								"api",
								"v1",
								"addresses",
								"delete",
								"4"
							]
						}
					},
					"response": []
				}
			]
		}
	]
}